Workbook

Sheet 📊 Dashboard
A1: ✨ SMART EVENT PLANNER PRO — Primavera Events Group
A2: Tu herramienta profesional de planeación de eventos
A4: ⚙️ CONFIGURACIÓN DEL EVENTO
A5: Nombre del evento | B5: Boda Sofía & Rodrigo | C5: ⏳ Días para el evento:
A6: Tipo de evento | B6: Boda | C6: =IF(B7="","—",MAX(0,B7-TODAY())) -> 0
A7: Fecha del evento | B7: 45976 | C7: días restantes
A8: Lugar | B8: Hacienda La Primavera, Morelos
A9: Número de invitados | B9: 150
A10: Presupuesto total ($MXN) | B10: 180000
A12: 💰 PRESUPUESTO GASTADO | D12: ✅ TAREAS COMPLETADAS | G12: 👥 INVITADOS CONFIRMADOS | J12: 📦 SERVICIOS SELEC.
A13: =IFERROR('💰 Presupuesto'!H52,0) -> 2500 | D13: =COUNTIF('✅ Checklist'!E5:E60,"✓") -> 6 | G13: =COUNTIF('👥 Invitados'!D5:D204,"Sí") -> 6 | J13: =COUNTIF('📦 Catálogo'!G5:G120,"✓") -> 0
A15: 💰 RESUMEN DE PRESUPUESTO | G15: ⚠️ ALERTAS INTELIGENTES
A16: Presupuesto Total | B16: =B10 -> 180000 | G16: =IF(AND(B7-TODAY()<90,COUNTIF('📦 Catálogo'!B5:B120,"*fotógrafo*")+COUNTIF('📦 Catálogo'!G5:G120,"✓")=0),"🔴 Faltan menos de 90 días y no tienes fotógrafo","🟢 Fotografía en orden") -> 🔴 Faltan menos de 90 días y no tienes fotógrafo
A17: Total Estimado (Catálogo) | B17: =IFERROR('💰 Presupuesto'!E58,0) -> 299200 | G17: =IF(B7-TODAY()<60,"🟠 Faltan menos de 60 días — confirma DJ y música","🟢 Música en orden") -> 🟠 Faltan menos de 60 días — confirma DJ y música
A18: Total Real (Gastado) | B18: =IFERROR('💰 Presupuesto'!G58,0) -> 294700 | G18: =IF(IFERROR(B18/B16,0)>0.8,"🔴 Superaste el 80% del presupuesto","🟢 Presupuesto bajo control") -> 🔴 Superaste el 80% del presupuesto
A19: Total Anticipos Pagados | B19: =IFERROR('💰 Presupuesto'!H58,0) -> 137800 | G19: =IF(AND(B7-TODAY()<30,IFERROR(COUNTIF('👥 Invitados'!D5:D204,"Sí")/B9,0)<0.5),"🟡 Menos del 50% de confirmaciones a 30 días","🟢 Confirmaciones en orden") -> 🟡 Menos del 50% de confirmaciones a 30 días
A20: Saldo Pendiente | B20: =IFERROR('💰 Presupuesto'!I58,0) -> 156900 | G20: =IF(B7-TODAY()<7,"🔴 ¡SEMANA DEL EVENTO! Verifica últimos pagos y logística","🟢 Aún hay tiempo") -> 🔴 ¡SEMANA DEL EVENTO! Verifica últimos pagos y logística
A21: Disponible (Presupuesto-Estimado) | B21: =B16-B17 -> -119200
A22: % Presupuesto Utilizado | B22: =IFERROR(B18/B16,0) -> 1.6372222

Sheet 💰 Presupuesto
A1: 💰 PRESUPUESTO DEL EVENTO
A2: Gestiona costos estimados, reales y saldos pendientes
A3: N° | B3: Categoría | C3: Servicio / Proveedor | D3: Descripción | E3: Costo Estimado | F3: % del Total | G3: Costo Real | H3: Anticipo Pagado | I3: Saldo Pendiente | J3: Estado | K3: Notas
A4: 🏛️ Locación & Logística
A5: 1 | B5: 🏛️ Locación & Logística | C5: Salón de eventos — Hacienda La Primavera | E5: 45000 | F5: =IFERROR(E5/E$58,0) -> 0.15040107 | G5: 45000 | H5: 20000 | I5: =IFERROR(G5-H5,0) -> 25000 | J5: Anticipo pagado
A6: 2 | B6: 🏛️ Locación & Logística | C6: Valet Parking — Staff Externo | E6: 5000 | F6: =IFERROR(E6/E$58,0) -> 0.01671123 | G6: 5000 | H6: 2000 | I6: =IFERROR(G6-H6,0) -> 3000 | J6: Anticipo pagado
A7: 3 | B7: 🏛️ Locación & Logística | C7: Generador eléctrico — Rentas López | E7: 3500 | F7: =IFERROR(E7/E$58,0) -> 0.011697861 | G7: 3500 | H7: 0 | I7: =IFERROR(G7-H7,0) -> 3500 | J7: Pendiente
A8: 4 | B8: 🏛️ Locación & Logística | C8: Seguridad privada — SecureEvents | E8: 4000 | F8: =IFERROR(E8/E$58,0) -> 0.013368984 | G8: 4000 | H8: 4000 | I8: =IFERROR(G8-H8,0) -> 0 | J8: Pagado
A9: 🍽️ Banquete & Bebidas
A10: 5 | B10: 🍽️ Banquete & Bebidas | C10: Banquete 3 tiempos — Catering Gourmet MX | E10: 35000 | F10: =IFERROR(E10/E$58,0) -> 0.11697861 | G10: 35000 | H10: 15000 | I10: =IFERROR(G10-H10,0) -> 20000 | J10: Anticipo pagado
A11: 6 | B11: 🍽️ Banquete & Bebidas | C11: Pastel de bodas — Dulcería Arte | E11: 8000 | F11: =IFERROR(E11/E$58,0) -> 0.026737968 | G11: 8500 | H11: 4000 | I11: =IFERROR(G11-H11,0) -> 4500 | J11: Anticipo pagado
A12: 7 | B12: 🍽️ Banquete & Bebidas | C12: Barra libre — Bar Móvil Premium | E12: 12000 | F12: =IFERROR(E12/E$58,0) -> 0.040106952 | G12: 12000 | H12: 6000 | I12: =IFERROR(G12-H12,0) -> 6000 | J12: Anticipo pagado
A13: 8 | B13: 🍽️ Banquete & Bebidas | C13: Taquiza madrugada — Tacos El Compadre | E13: 6000 | F13: =IFERROR(E13/E$58,0) -> 0.020053476 | G13: 6000 | H13: 0 | I13: =IFERROR(G13-H13,0) -> 6000 | J13: Pendiente
A14: 🎧 Entretenimiento
A15: 9 | B15: 🎧 Entretenimiento | C15: DJ profesional — DJ Alex Beats | E15: 8000 | F15: =IFERROR(E15/E$58,0) -> 0.026737968 | G15: 8000 | H15: 4000 | I15: =IFERROR(G15-H15,0) -> 4000 | J15: Anticipo pagado
A16: 10 | B16: 🎧 Entretenimiento | C16: Mariachi — Mariachi Sol de México | E16: 6000 | F16: =IFERROR(E16/E$58,0) -> 0.020053476 | G16: 6000 | H16: 6000 | I16: =IFERROR(G16-H16,0) -> 0 | J16: Pagado
A17: 11 | B17: 🎧 Entretenimiento | C17: Show sorpresa — Batucada Ritmo Vivo | E17: 5000 | F17: =IFERROR(E17/E$58,0) -> 0.01671123 | G17: 5000 | H17: 0 | I17: =IFERROR(G17-H17,0) -> 5000 | J17: Pendiente
A18: 12 | B18: 🎧 Entretenimiento | C18: Maestro de ceremonias — MC Eventos Pro | E18: 3500 | F18: =IFERROR(E18/E$58,0) -> 0.011697861 | G18: 3500 | H18: 3500 | I18: =IFERROR(G18-H18,0) -> 0 | J18: Pagado
A19: 📸 Foto & Video
A20: 13 | B20: 📸 Foto & Video | C20: Fotógrafo — Luis Mendoza Photography | E20: 15000 | F20: =IFERROR(E20/E$58,0) -> 0.05013369 | G20: 15000 | H20: 7500 | I20: =IFERROR(G20-H20,0) -> 7500 | J20: Anticipo pagado
A21: 14 | B21: 📸 Foto & Video | C21: Videógrafo + Drone — Pixel Films | E21: 12000 | F21: =IFERROR(E21/E$58,0) -> 0.040106952 | G21: 12000 | H21: 6000 | I21: =IFERROR(G21-H21,0) -> 6000 | J21: Anticipo pagado
A22: 15 | B22: 📸 Foto & Video | C22: Same Day Edit — Pixel Films | E22: 3000 | F22: =IFERROR(E22/E$58,0) -> 0.010026738 | G22: 3000 | H22: 0 | I22: =IFERROR(G22-H22,0) -> 3000 | J22: Pendiente
A23: 💄 Belleza & Imagen
A24: 16 | B24: 💄 Belleza & Imagen | C24: Maquillista — Glam Studio | E24: 4500 | F24: =IFERROR(E24/E$58,0) -> 0.015040107 | G24: 4500 | H24: 2000 | I24: =IFERROR(G24-H24,0) -> 2500 | J24: Anticipo pagado
A25: 17 | B25: 💄 Belleza & Imagen | C25: Peinadora / Estilista — Glam Studio | E25: 3500 | F25: =IFERROR(E25/E$58,0) -> 0.011697861 | G25: 3500 | H25: 1500 | I25: =IFERROR(G25-H25,0) -> 2000 | J25: Anticipo pagado
A26: 18 | B26: 💄 Belleza & Imagen | C26: Barbero (novio) — Barber Kings | E26: 800 | F26: =IFERROR(E26/E$58,0) -> 0.0026737968 | G26: 800 | H26: 800 | I26: =IFERROR(G26-H26,0) -> 0 | J26: Pagado
A27: 👗 Vestuario
A28: 19 | B28: 👗 Vestuario | C28: Vestido de novia — Bridal House Cuernavaca | E28: 18000 | F28: =IFERROR(E28/E$58,0) -> 0.060160428 | G28: 18000 | H28: 9000 | I28: =IFERROR(G28-H28,0) -> 9000 | J28: Anticipo pagado
A29: 20 | B29: 👗 Vestuario | C29: Traje del novio — Fashion Men | E29: 6000 | F29: =IFERROR(E29/E$58,0) -> 0.020053476 | G29: 6000 | H29: 3000 | I29: =IFERROR(G29-H29,0) -> 3000 | J29: Anticipo pagado
A30: 21 | B30: 👗 Vestuario | C30: Vestidos de damas (5) — Boutique Elegance | E30: 7500 | F30: =IFERROR(E30/E$58,0) -> 0.025066845 | G30: 7500 | H30: 3500 | I30: =IFERROR(G30-H30,0) -> 4000 | J30: Anticipo pagado
A31: 💃 Coreografía & Show
A32: 22 | B32: 💃 Coreografía & Show | C32: Coreógrafo — Dance Academy Pro | E32: 4000 | F32: =IFERROR(E32/E$58,0) -> 0.013368984 | G32: 4000 | H32: 2000 | I32: =IFERROR(G32-H32,0) -> 2000 | J32: Anticipo pagado
A33: 23 | B33: 💃 Coreografía & Show | C33: Clases de baile (10 sesiones) — Dance Academy Pro | E33: 3000 | F33: =IFERROR(E33/E$58,0) -> 0.010026738 | G33: 3000 | H33: 3000 | I33: =IFERROR(G33-H33,0) -> 0 | J33: Pagado
A34: 🌸 Decoración & Diseño
A35: 24 | B35: 🌸 Decoración & Diseño | C35: Decorador principal — Deco Dreams | E35: 15000 | F35: =IFERROR(E35/E$58,0) -> 0.05013369 | G35: 15000 | H35: 7000 | I35: =IFERROR(G35-H35,0) -> 8000 | J35: Anticipo pagado
A36: 25 | B36: 🌸 Decoración & Diseño | C36: Arreglos florales — Floral Art Studio | E36: 8000 | F36: =IFERROR(E36/E$58,0) -> 0.026737968 | G36: 8000 | H36: 4000 | I36: =IFERROR(G36-H36,0) -> 4000 | J36: Anticipo pagado
A37: 26 | B37: 🌸 Decoración & Diseño | C37: Iluminación ambiental — Luz & Ambiente | E37: 5000 | F37: =IFERROR(E37/E$58,0) -> 0.01671123 | G37: 5000 | H37: 2500 | I37: =IFERROR(G37-H37,0) -> 2500 | J37: Anticipo pagado
A38: 27 | B38: 🌸 Decoración & Diseño | C38: Mantelería y vajilla — Rentas Elegance | E38: 4000 | F38: =IFERROR(E38/E$58,0) -> 0.013368984 | G38: 4000 | H38: 0 | I38: =IFERROR(G38-H38,0) -> 4000 | J38: Pendiente
A39: 💌 Papelería & Diseño
A40: 28 | B40: 💌 Papelería & Diseño | C40: Invitaciones físicas (200) — Imprenta Creativa | E40: 3500 | F40: =IFERROR(E40/E$58,0) -> 0.011697861 | G40: 3500 | H40: 3500 | I40: =IFERROR(G40-H40,0) -> 0 | J40: Pagado
A41: 29 | B41: 💌 Papelería & Diseño | C41: Invitaciones digitales — Design Studio | E41: 1500 | F41: =IFERROR(E41/E$58,0) -> 0.005013369 | G41: 1500 | H41: 1500 | I41: =IFERROR(G41-H41,0) -> 0 | J41: Pagado
A42: 30 | B42: 💌 Papelería & Diseño | C42: Señalética del evento — Design Studio | E42: 1200 | F42: =IFERROR(E42/E$58,0) -> 0.0040106952 | G42: 1200 | H42: 0 | I42: =IFERROR(G42-H42,0) -> 1200 | J42: Pendiente
A43: 🚗 Transporte
A44: 31 | B44: 🚗 Transporte | C44: Transporte invitados (2 vans) — Trans VIP | E44: 5000 | F44: =IFERROR(E44/E$58,0) -> 0.01671123 | G44: 5000 | H44: 2500 | I44: =IFERROR(G44-H44,0) -> 2500 | J44: Anticipo pagado
A45: 32 | B45: 🚗 Transporte | C45: Limusina novios — Limo Service MX | E45: 4500 | F45: =IFERROR(E45/E$58,0) -> 0.015040107 | G45: 4500 | H45: 4500 | I45: =IFERROR(G45-H45,0) -> 0 | J45: Pagado
A46: 🧑 Staff Operativo
A47: 33 | B47: 🧑 Staff Operativo | C47: Meseros (10) — Staff Events | E47: 8000 | F47: =IFERROR(E47/E$58,0) -> 0.026737968 | G47: 8000 | H47: 0 | I47: =IFERROR(G47-H47,0) -> 8000 | J47: Pendiente
A48: 34 | B48: 🧑 Staff Operativo | C48: Hostess (4) — Staff Events | E48: 3200 | F48: =IFERROR(E48/E$58,0) -> 0.010695187 | G48: 3200 | H48: 0 | I48: =IFERROR(G48-H48,0) -> 3200 | J48: Pendiente
A49: 35 | B49: 🧑 Staff Operativo | C49: Coordinador día del evento — Primavera Events Group | E49: 5000 | F49: =IFERROR(E49/E$58,0) -> 0.01671123 | G49: 5000 | H49: 5000 | I49: =IFERROR(G49-H49,0) -> 0 | J49: Pagado
A50: 🎁 Experiencia & Extras
A51: 36 | B51: 🎁 Experiencia & Extras | C51: Souvenirs (150) — Recuerdos MX | E51: 4500 | F51: =IFERROR(E51/E$58,0) -> 0.015040107 | G51: 4500 | H51: 0 | I51: =IFERROR(G51-H51,0) -> 4500 | J51: Pendiente
A52: 37 | B52: 🎁 Experiencia & Extras | C52: Letras gigantes LED — Deco Dreams | E52: 2500 | F52: =IFERROR(E52/E$58,0) -> 0.008355615 | G52: 2500 | H52: 2500 | I52: =IFERROR(G52-H52,0) -> 0 | J52: Pagado
A53: 38 | B53: 🎁 Experiencia & Extras | C53: Fuegos artificiales fríos — Pirotecnia Arte | E53: 3000 | F53: =IFERROR(E53/E$58,0) -> 0.010026738 | G53: 3000 | H53: 0 | I53: =IFERROR(G53-H53,0) -> 3000 | J53: Pendiente
A54: 🧾 Administrativo
A55: 39 | B55: 🧾 Administrativo | C55: Seguro del evento — Seguros Eventos | E55: 2000 | F55: =IFERROR(E55/E$58,0) -> 0.006684492 | G55: 2000 | H55: 2000 | I55: =IFERROR(G55-H55,0) -> 0 | J55: Pagado
A56: 40 | B56: 🧾 Administrativo | C56: Gastos imprevistos — — | E56: 5000 | F56: =IFERROR(E56/E$58,0) -> 0.01671123 | G56: 0 | H56: 0 | I56: =IFERROR(G56-H56,0) -> 0 | J56: Pendiente
A58: TOTALES GENERALES | E58: =SUM(E4:E57) -> 299200 | F58: ="100%" -> 100% | G58: =SUM(G4:G57) -> 294700 | H58: =SUM(H4:H57) -> 137800 | I58: =SUM(I4:I57) -> 156900

Sheet 📦 Catálogo
A1: 📦 CATÁLOGO COMPLETO DE SERVICIOS
A2: Selecciona los servicios — se reflejarán en el presupuesto automáticamente
A3: N° | B3: Categoría | C3: Servicio | D3: Descripción | E3: Costo Est. ($) | F3: Prioridad | G3: Seleccionado | H3: Notas
A4: 🏛️ Locación & Logística
A5: 1 | B5: 🏛️ Locación & Logística | C5: Salón de eventos | D5: Espacio cerrado con clima y equipamiento | E5: 45000 | F5: Alta | G5: —
A6: 2 | B6: 🏛️ Locación & Logística | C6: Jardín / Hacienda | D6: Espacio abierto o semi-abierto | E6: 40000 | F6: Alta | G6: —
A7: 3 | B7: 🏛️ Locación & Logística | C7: Terraza | D7: Vista panorámica y ambiente al aire libre | E7: 30000 | F7: Media | G7: —
A8: 4 | B8: 🏛️ Locación & Logística | C8: Permisos municipales | D8: Trámites legales para el evento | E8: 2000 | F8: Alta | G8: —
A9: 5 | B9: 🏛️ Locación & Logística | C9: Planta de luz / Generador | D9: Respaldo eléctrico garantizado | E9: 3500 | F9: Alta | G9: —
A10: 6 | B10: 🏛️ Locación & Logística | C10: Sanitarios móviles | D10: Para eventos en espacios abiertos | E10: 2500 | F10: Media | G10: —
A11: 7 | B11: 🏛️ Locación & Logística | C11: Estacionamiento / Valet parking | D11: Servicio de estacionamiento para invitados | E11: 5000 | F11: Media | G11: —
A12: 8 | B12: 🏛️ Locación & Logística | C12: Seguridad privada | D12: Personal de seguridad certificado | E12: 4000 | F12: Alta | G12: —
A13: 9 | B13: 🏛️ Locación & Logística | C13: Protección civil | D13: Requerido en eventos +100 personas | E13: 1500 | F13: Alta | G13: —
A14: 🍽️ Banquete & Bebidas
A15: 10 | B15: 🍽️ Banquete & Bebidas | C15: Banquete 3 tiempos | D15: Entrada, plato fuerte y postre por persona | E15: 35000 | F15: Alta | G15: —
A16: 11 | B16: 🍽️ Banquete & Bebidas | C16: Buffet | D16: Variedad de platillos a libre servicio | E16: 28000 | F16: Alta | G16: —
A17: 12 | B17: 🍽️ Banquete & Bebidas | C17: Taquiza | D17: Servicio de tacos variados | E17: 8000 | F17: Alta | G17: —
A18: 13 | B18: 🍽️ Banquete & Bebidas | C18: Mesa de postres | D18: Variedad de dulces y postres artesanales | E18: 4500 | F18: Media | G18: —
A19: 14 | B19: 🍽️ Banquete & Bebidas | C19: Pastel de bodas/XV | D19: Pastel temático o tradicional | E19: 8000 | F19: Alta | G19: —
A20: 15 | B20: 🍽️ Banquete & Bebidas | C20: Candy bar | D20: Barra de dulces decorativa | E20: 3500 | F20: Media | G20: —
A21: 16 | B21: 🍽️ Banquete & Bebidas | C21: Barra libre | D21: Bebidas ilimitadas durante el evento | E21: 12000 | F21: Alta | G21: —
A22: 17 | B22: 🍽️ Banquete & Bebidas | C22: Mixología | D22: Cócteles artesanales y presentaciones especiales | E22: 5000 | F22: Media | G22: —
A23: 18 | B23: 🍽️ Banquete & Bebidas | C23: Coffee break | D23: Café, té e infusiones durante el evento | E23: 2000 | F23: Baja | G23: —
A24: 19 | B24: 🍽️ Banquete & Bebidas | C24: Tornaboda | D24: Antojitos nocturnos al cierre del evento | E24: 6000 | F24: Media | G24: —
A25: 🎧 Entretenimiento
A26: 20 | B26: 🎧 Entretenimiento | C26: DJ profesional | D26: Música de fondo y pista de baile | E26: 8000 | F26: Alta | G26: —
A27: 21 | B27: 🎧 Entretenimiento | C27: Grupo musical en vivo | D27: Banda o grupo en vivo durante la cena | E27: 15000 | F27: Media | G27: —
A28: 22 | B28: 🎧 Entretenimiento | C28: Mariachi | D28: Serenata y repertorio tradicional | E28: 6000 | F28: Media | G28: —
A29: 23 | B29: 🎧 Entretenimiento | C29: Saxofonista | D29: Música ambient de fondo | E29: 3500 | F29: Media | G29: —
A30: 24 | B30: 🎧 Entretenimiento | C30: Violinista | D30: Música clásica para ceremonia o cena | E30: 3000 | F30: Media | G30: —
A31: 25 | B31: 🎧 Entretenimiento | C31: Batucada | D31: Show de percusión y energía | E31: 5000 | F31: Media | G31: —
A32: 26 | B32: 🎧 Entretenimiento | C32: Show sorpresa | D32: Actuación o número especial | E32: 6000 | F32: Media | G32: —
A33: 27 | B33: 🎧 Entretenimiento | C33: Maestro de ceremonias | D33: Conductor del evento y dinámica general | E33: 3500 | F33: Alta | G33: —
A34: 28 | B34: 🎧 Entretenimiento | C34: Cabina de fotos | D34: Impresión instantánea de recuerdos | E34: 4500 | F34: Media | G34: —
A35: 29 | B35: 🎧 Entretenimiento | C35: Espejo mágico | D35: Fotos interactivas con efectos digitales | E35: 5000 | F35: Media | G35: —
A36: 30 | B36: 🎧 Entretenimiento | C36: Pista LED | D36: Pista de baile iluminada | E36: 8000 | F36: Media | G36: —
A37: 31 | B37: 🎧 Entretenimiento | C37: Robot LED / Show neón | D37: Performance visual de impacto | E37: 7000 | F37: Baja | G37: —
A38: 📸 Foto & Video
A39: 32 | B39: 📸 Foto & Video | C39: Fotógrafo profesional | D39: Cobertura completa del evento | E39: 15000 | F39: Alta | G39: —
A40: 33 | B40: 📸 Foto & Video | C40: Videógrafo | D40: Video cinematográfico del evento | E40: 12000 | F40: Alta | G40: —
A41: 34 | B41: 📸 Foto & Video | C41: Drone | D41: Tomas aéreas del evento y locación | E41: 4000 | F41: Media | G41: —
A42: 35 | B42: 📸 Foto & Video | C42: Same Day Edit | D42: Video editado el mismo día del evento | E42: 3000 | F42: Media | G42: —
A43: 36 | B43: 📸 Foto & Video | C43: Sesión pre-evento | D43: Fotos de preparativos y getting ready | E43: 3500 | F43: Media | G43: —
A44: 37 | B44: 📸 Foto & Video | C44: Álbum impreso | D44: Álbum de fotos profesional personalizado | E44: 4500 | F44: Media | G44: —
A45: 💄 Belleza & Imagen
A46: 38 | B46: 💄 Belleza & Imagen | C46: Maquillista | D46: Maquillaje profesional para la quinceañera/novia | E46: 4500 | F46: Alta | G46: —
A47: 39 | B47: 💄 Belleza & Imagen | C47: Peinador / Estilista | D47: Peinado profesional y acabados | E47: 3500 | F47: Alta | G47: —
A48: 40 | B48: 💄 Belleza & Imagen | C48: Barbero (novio) | D48: Arreglo profesional para el novio | E48: 800 | F48: Media | G48: —
A49: 41 | B49: 💄 Belleza & Imagen | C49: Spa / Tratamientos previos | D49: Relajación y cuidado pre-evento | E49: 2500 | F49: Media | G49: —
A50: 42 | B50: 💄 Belleza & Imagen | C50: Prueba de maquillaje | D50: Sesión de prueba anticipada | E50: 1500 | F50: Alta | G50: —
A51: 👗 Vestuario
A52: 43 | B52: 👗 Vestuario | C52: Vestido de novia / XV | D52: Vestido principal del evento | E52: 18000 | F52: Alta | G52: —
A53: 44 | B53: 👗 Vestuario | C53: Traje del novio | D53: Traje sastre o smoking | E53: 6000 | F53: Alta | G53: —
A54: 45 | B54: 👗 Vestuario | C54: Vestidos de damas | D54: Conjunto de vestidos del chambelanes/damas | E54: 7500 | F54: Media | G54: —
A55: 46 | B55: 👗 Vestuario | C55: Renta de smoking | D55: Smoking para el padre o chambelanes | E55: 3000 | F55: Media | G55: —
A56: 47 | B56: 👗 Vestuario | C56: Accesorios (velo, tiara, etc.) | D56: Complementos del vestuario | E56: 2500 | F56: Media | G56: —
A57: 48 | B57: 👗 Vestuario | C57: Zapatos | D57: Calzado especial para el evento | E57: 2000 | F57: Media | G57: —
A58: 49 | B58: 👗 Vestuario | C58: Joyería | D58: Aretes, collar, brazalete | E58: 3000 | F58: Media | G58: —
A59: 💃 Coreografía & Show
A60: 50 | B60: 💃 Coreografía & Show | C60: Coreógrafo profesional | D60: Diseño y dirección de baile | E60: 4000 | F60: Alta | G60: —
A61: 51 | B61: 💃 Coreografía & Show | C61: Clases de baile | D61: Sesiones de ensayo para el vals/vals sorpresa | E61: 3000 | F61: Alta | G61: —
A62: 52 | B62: 💃 Coreografía & Show | C62: Ensayos grupales | D62: Coordinación con chambelanes o pareja | E62: 1500 | F62: Alta | G62: —
A63: 53 | B63: 💃 Coreografía & Show | C63: Bailarines profesionales | D63: Performance de apertura o cierre | E63: 5000 | F63: Media | G63: —
A64: 54 | B64: 💃 Coreografía & Show | C64: Performance especial | D64: Número artístico personalizado | E64: 4000 | F64: Media | G64: —
A65: 🌸 Decoración & Diseño
A66: 55 | B66: 🌸 Decoración & Diseño | C66: Wedding / Event Planner | D66: Coordinación integral del evento | E66: 15000 | F66: Alta | G66: —
A67: 56 | B67: 🌸 Decoración & Diseño | C67: Decorador principal | D67: Montaje y concepto visual completo | E67: 15000 | F67: Alta | G67: —
A68: 57 | B68: 🌸 Decoración & Diseño | C68: Diseño floral | D68: Flores frescas: ramos, centros, altar | E68: 8000 | F68: Alta | G68: —
A69: 58 | B69: 🌸 Decoración & Diseño | C69: Centros de mesa | D69: Arreglos para cada mesa de invitados | E69: 5000 | F69: Alta | G69: —
A70: 59 | B70: 🌸 Decoración & Diseño | C70: Backdrop / Altar | D70: Escenario principal o altar de ceremonia | E70: 6000 | F70: Alta | G70: —
A71: 60 | B71: 🌸 Decoración & Diseño | C71: Iluminación ambiental | D71: Luces decorativas, velas y LED | E71: 5000 | F71: Alta | G71: —
A72: 61 | B72: 🌸 Decoración & Diseño | C72: Mobiliario (mesas, sillas, lounges) | D72: Renta de muebles temáticos | E72: 4500 | F72: Media | G72: —
A73: 62 | B73: 🌸 Decoración & Diseño | C73: Mantelería premium | D73: Manteles, servilletas y faldones | E73: 2500 | F73: Media | G73: —
A74: 63 | B74: 🌸 Decoración & Diseño | C74: Vajilla especial | D74: Vajilla exclusiva o de diseño | E74: 3000 | F74: Media | G74: —
A75: 64 | B75: 🌸 Decoración & Diseño | C75: Cristalería | D75: Copas y vasos de cristal premium | E75: 2000 | F75: Media | G75: —
A76: 💡 Producción & Montaje
A77: 65 | B77: 💡 Producción & Montaje | C77: Iluminación arquitectónica | D77: Iluminación profesional de la locación | E77: 6000 | F77: Alta | G77: —
A78: 66 | B78: 💡 Producción & Montaje | C78: Audio profesional | D78: Sistema de sonido para todo el evento | E78: 5000 | F78: Alta | G78: —
A79: 67 | B79: 💡 Producción & Montaje | C79: Pantallas LED | D79: Proyección de video y presentaciones | E79: 4000 | F79: Media | G79: —
A80: 68 | B80: 💡 Producción & Montaje | C80: Proyector | D80: Proyector para presentaciones o fotos | E80: 2000 | F80: Media | G80: —
A81: 69 | B81: 💡 Producción & Montaje | C81: Estructuras / escenarios | D81: Tarimas y estructuras especiales | E81: 5000 | F81: Media | G81: —
A82: 💌 Papelería & Diseño Gráfico
A83: 70 | B83: 💌 Papelería & Diseño Gráfico | C83: Invitaciones físicas | D83: Invitaciones impresas personalizadas | E83: 3500 | F83: Alta | G83: —
A84: 71 | B84: 💌 Papelería & Diseño Gráfico | C84: Invitaciones digitales | D84: Invitaciones con animación para WhatsApp | E84: 1500 | F84: Alta | G84: —
A85: 72 | B85: 💌 Papelería & Diseño Gráfico | C85: Save the date | D85: Tarjeta anticipada de la fecha | E85: 1200 | F85: Media | G85: —
A86: 73 | B86: 💌 Papelería & Diseño Gráfico | C86: Menús impresos | D86: Menú del banquete por persona | E86: 800 | F86: Baja | G86: —
A87: 74 | B87: 💌 Papelería & Diseño Gráfico | C87: Números y nombres de mesa | D87: Señalética de mesas | E87: 600 | F87: Baja | G87: —
A88: 75 | B88: 💌 Papelería & Diseño Gráfico | C88: Señalética del evento | D88: Guías, rótulos y señales decorativas | E88: 1200 | F88: Media | G88: —
A89: 76 | B89: 💌 Papelería & Diseño Gráfico | C89: Branding del evento | D89: Identidad visual completa del evento | E89: 2500 | F89: Media | G89: —
A90: 🚗 Transporte
A91: 77 | B91: 🚗 Transporte | C91: Transporte de invitados | D91: Vans o autobuses para traslados | E91: 5000 | F91: Media | G91: —
A92: 78 | B92: 🚗 Transporte | C92: Limusina para novios | D92: Traslado especial de los novios | E92: 4500 | F92: Media | G92: —
A93: 79 | B93: 🚗 Transporte | C93: Auto clásico / decorado | D93: Vehículo especial para la quinceañera | E93: 3500 | F93: Media | G93: —
A94: 80 | B94: 🚗 Transporte | C94: Autobuses (distancias largas) | D94: Para invitados foráneos | E94: 8000 | F94: Media | G94: —
A95: 🧑 Staff Operativo
A96: 81 | B96: 🧑 Staff Operativo | C96: Coordinador día del evento | D96: Supervisión total durante el evento | E96: 5000 | F96: Alta | G96: —
A97: 82 | B97: 🧑 Staff Operativo | C97: Hostess de bienvenida | D97: Recepción y guía de invitados | E97: 3200 | F97: Alta | G97: —
A98: 83 | B98: 🧑 Staff Operativo | C98: Meseros profesionales | D98: Servicio de mesa durante el banquete | E98: 8000 | F98: Alta | G98: —
A99: 84 | B99: 🧑 Staff Operativo | C99: Capitán de meseros | D99: Supervisión del servicio de alimentos | E99: 2500 | F99: Alta | G99: —
A100: 85 | B100: 🧑 Staff Operativo | C100: Personal de limpieza | D100: Mantenimiento durante el evento | E100: 1500 | F100: Alta | G100: —
...

Sheet 👥 Invitados
A1: 👥 LISTA DE INVITADOS
A2: Gestiona confirmaciones, mesas y restricciones alimenticias
A3: Total invitados esperados: | B3: ='📊 Dashboard'!B9 -> 150 | C3: ✅ Confirmados: | D3: =COUNTIF(D6:D205,"Sí") -> 6 | E3: ⏳ Pendientes: | F3: =COUNTIF(D6:D205,"Pendiente") -> 3 | G3: ❌ No asistirán: | H3: =COUNTIF(D6:D205,"No") -> 1 | I3: 👥 Total personas: | J3: =SUMIF(D6:D205,"Sí",E6:E205)+SUMIF(D6:D205,"Pendiente",E6:E205) -> 8
A5: N° | B5: Nombre completo | C5: Familia / Grupo | D5: Confirmación | E5: Acompañantes | F5: Total personas | G5: Mesa asignada | H5: Restricción alimenticia | I5: Teléfono | J5: Notas
A6: 1 | B6: García Martínez | C6: Familia García | D6: Sí | E6: 1 | F6: 2 | G6: Mesa 1 | H6: Ninguna | I6: 55-1234-5678
A7: 2 | B7: López Hernández | C7: Amigos novio | D7: Sí | E7: 0 | F7: 1 | G7: Mesa 2 | H7: Vegetariano | I7: 55-2345-6789
A8: 3 | B8: Rodríguez Pérez | C8: Familia novia | D8: Pendiente | E8: 2 | F8: 3 | H8: Ninguna | I8: 55-3456-7890
A9: 4 | B9: Martínez González | C9: Trabajo | D9: Sí | E9: 1 | F9: 2 | G9: Mesa 3 | H9: Celiaco | I9: 55-4567-8901
A10: 5 | B10: Sánchez Torres | C10: Amigos novia | D10: No | E10: 0 | F10: 1 | H10: Ninguna | I10: 55-5678-9012
A11: 6 | B11: Jiménez Flores | C11: Familia García | D11: Sí | E11: 0 | F11: 1 | G11: Mesa 1 | H11: Alérgico mariscos | I11: 55-6789-0123
A12: 7 | B12: Morales Ruiz | C12: Amigos novio | D12: Pendiente | E12: 1 | F12: 2 | H12: Ninguna | I12: 55-7890-1234
A13: 8 | B13: Hernández Cruz | C13: Trabajo novia | D13: Sí | E13: 1 | F13: 2 | G13: Mesa 4 | H13: Ninguna | I13: 55-8901-2345
A14: 9 | B14: Vázquez Díaz | C14: Familia novia | D14: Sí | E14: 2 | F14: 3 | G14: Mesa 2 | H14: Ninguna | I14: 55-9012-3456
A15: 10 | B15: Reyes Moreno | C15: Amigos | D15: Pendiente | E15: 0 | F15: 1 | H15: Vegetariano | I15: 55-0123-4567
A16: 11 | F16: =IF(D16="","",E16+1)
A17: 12 | F17: =IF(D17="","",E17+1)
A18: 13 | F18: =IF(D18="","",E18+1)
A19: 14 | F19: =IF(D19="","",E19+1)
A20: 15 | F20: =IF(D20="","",E20+1)
A21: 16 | F21: =IF(D21="","",E21+1)
A22: 17 | F22: =IF(D22="","",E22+1)
A23: 18 | F23: =IF(D23="","",E23+1)
A24: 19 | F24: =IF(D24="","",E24+1)
A25: 20 | F25: =IF(D25="","",E25+1)
A26: 21 | F26: =IF(D26="","",E26+1)
A27: 22 | F27: =IF(D27="","",E27+1)
... A205: 200 | F205: =IF(D205="","",E205+1)

Sheet ✅ Checklist
A1: ✅ CHECKLIST POR FASES
A2: Tareas organizadas por etapa — marca ✓ cuando completes cada una
A3: 📊 PROGRESO GENERAL | E3: =COUNTIF(E5:E200,"✓")&" de "&COUNTA(A5:A200)&" tareas completadas" -> 6 de 48 tareas completadas | G3: =IFERROR(COUNTIF(E5:E200,"✓")/COUNTA(A5:A200),0) -> 0.125
A4: N° | B4: Tarea | C4: Responsable | D4: Fecha Límite | E4: Estado | F4: Completado | G4: Notas
A5: 📅 FASE 1: 12-6 MESES ANTES DEL EVENTO
A6: 1 | B6: Definir presupuesto total del evento | C6: Novios/Familia | D6: 12 meses antes | E6: ✓ | F6: =IF(E6="✓","✅ Completado","⏳ Pendiente") -> ✅ Completado
A7: 2 | B7: Elegir y reservar la locación/salón | C7: Novios + Planner | D7: 12 meses antes | E7: ✓ | F7: =IF(E7="✓","✅ Completado","⏳ Pendiente") -> ✅ Completado
A8: 3 | B8: Contratar wedding planner | C8: Novios | D8: 11 meses antes | E8: ✓ | F8: =IF(E8="✓","✅ Completado","⏳ Pendiente") -> ✅ Completado
A9: 4 | B9: Establecer lista preliminar de invitados | C9: Familia | D9: 10 meses antes | E9: ✓ | F9: =IF(E9="✓","✅ Completado","⏳ Pendiente") -> ✅ Completado
A10: 5 | B10: Elegir fecha y hora del evento | C10: Novios | D10: 11 meses antes | E10: ✓ | F10: =IF(E10="✓","✅ Completado","⏳ Pendiente") -> ✅ Completado
A11: 6 | B11: Definir tema y paleta de colores | C11: Novios + Decorador | D11: 10 meses antes | E11: ✓ | F11: =IF(E11="✓","✅ Completado","⏳ Pendiente") -> ✅ Completado
A12: 7 | B12: Contratar fotógrafo y videógrafo | C12: Planner | D12: 9 meses antes | F12: =IF(E12="✓","✅ Completado","⏳ Pendiente") -> ⏳ Pendiente
A13: 8 | B13: Elegir y reservar banquete/catering | C13: Planner | D13: 9 meses antes | F13: =IF(E13="✓","✅ Completado","⏳ Pendiente") -> ⏳ Pendiente
A14: 9 | B14: Seleccionar tipo de entretenimiento | C14: Novios + Planner | D14: 8 meses antes | F14: =IF(E14="✓","✅ Completado","⏳ Pendiente") -> ⏳ Pendiente
A15: 10 | B15: Abrir registro de mesa de regalos | C15: Novios | D15: 8 meses antes | F15: =IF(E15="✓","✅ Completado","⏳ Pendiente") -> ⏳ Pendiente
A16: 📅 FASE 2: 6-3 MESES ANTES DEL EVENTO
A17: 11 | B17: Elegir vestido de novia/quinceañera | C17: Novia | D17: 6 meses antes | F17: =IF(E17="✓","✅ Completado","⏳ Pendiente") -> ⏳ Pendiente
A18: 12 | B18: Contratar DJ o música en vivo | C18: Planner | D18: 6 meses antes | F18: =IF(E18="✓","✅ Completado","⏳ Pendiente") -> ⏳ Pendiente
A19: 13 | B19: Definir menú del banquete | C19: Pareja + Catering | D19: 5 meses antes | F19: =IF(E19="✓","✅ Completado","⏳ Pendiente") -> ⏳ Pendiente
A20: 14 | B20: Contratar decorador y diseño floral | C20: Planner | D20: 5 meses antes | F20: =IF(E20="✓","✅ Completado","⏳ Pendiente") -> ⏳ Pendiente
A21: 15 | B21: Diseñar e imprimir invitaciones | C21: Planner + Diseñador | D21: 5 meses antes | F21: =IF(E21="✓","✅ Completado","⏳ Pendiente") -> ⏳ Pendiente
A22: 16 | B22: Contratar coreógrafo | C22: Novios | D22: 5 meses antes | F22: =IF(E22="✓","✅ Completado","⏳ Pendiente") -> ⏳ Pendiente
A23: 17 | B23: Reservar hotel para invitados foráneos | C23: Planner | D23: 4 meses antes | F23: =IF(E23="✓","✅ Completado","⏳ Pendiente") -> ⏳ Pendiente
A24: 18 | B24: Contratar maquillista y estilista | C24: Novia | D24: 4 meses antes | F24: =IF(E24="✓","✅ Completado","⏳ Pendiente") -> ⏳ Pendiente
A25: 19 | B25: Enviar invitaciones | C25: Planner | D25: 3 meses antes | F25: =IF(E25="✓","✅ Completado","⏳ Pendiente") -> ⏳ Pendiente
A26: 20 | B26: Contratar transporte para invitados | C26: Planner | D26: 3 meses antes | F26: =IF(E26="✓","✅ Completado","⏳ Pendiente") -> ⏳ Pendiente
A27: 21 | B27: Contratar mariachi o entretenimiento extra | C27: Planner | D27: 3 meses antes | F27: =IF(E27="✓","✅ Completado","⏳ Pendiente") -> ⏳ Pendiente
A28: 22 | B28: Definir diseño de pastel | C28: Novios + Pastelero | D28: 3 meses antes | F28: =IF(E28="✓","✅ Completado","⏳ Pendiente") -> ⏳ Pendiente
A29: 📅 FASE 3: 3-1 MES ANTES DEL EVENTO
A30: 23 | B30: Confirmar todos los proveedores | C30: Planner | D30: 2 meses antes | F30: =IF(E30="✓","✅ Completado","⏳ Pendiente") -> ⏳ Pendiente
A31: 24 | B31: Iniciar clases de baile / ensayos | C31: Novios + Coreógrafo | D31: 2 meses antes | F31: =IF(E31="✓","✅ Completado","⏳ Pendiente") -> ⏳ Pendiente
A32: 25 | B32: Realizar prueba de maquillaje | C32: Novia + Maquillista | D32: 2 meses antes | F32: =IF(E32="✓","✅ Completado","⏳ Pendiente") -> ⏳ Pendiente
A33: 26 | B33: Seguimiento de confirmaciones de invitados | C33: Planner | D33: 6 semanas antes | F33: =IF(E33="✓","✅ Completado","⏳ Pendiente") -> ⏳ Pendiente
A34: 27 | B34: Diseñar seating plan (mesas) | C34: Planner | D34: 1.5 meses antes | F34: =IF(E34="✓","✅ Completado","⏳ Pendiente") -> ⏳ Pendiente
A35: 28 | B35: Coordinar música de ceremonia y recepción | C35: DJ + Planner | D35: 1 mes antes | F35: =IF(E35="✓","✅ Completado","⏳ Pendiente") -> ⏳ Pendiente
A36: 29 | B36: Entregar seating plan final | C36: Planner | D36: 3 semanas antes | F36: =IF(E36="✓","✅ Completado","⏳ Pendiente") -> ⏳ Pendiente
A37: 30 | B37: Confirmar menú definitivo con catering | C37: Planner + Catering | D37: 3 semanas antes | F37: =IF(E37="✓","✅ Completado","⏳ Pendiente") -> ⏳ Pendiente
A38: 31 | B38: Entregar timing del evento a proveedores | C38: Planner | D38: 2 semanas antes | F38: =IF(E38="✓","✅ Completado","⏳ Pendiente") -> ⏳ Pendiente
A39: 32 | B39: Preparar pagos finales | C39: Familia/Novios | D39: 2 semanas antes | F39: =IF(E39="✓","✅ Completado","⏳ Pendiente") -> ⏳ Pendiente
A40: 📅 FASE 4: SEMANA DEL EVENTO
A41: 33 | B41: Confirmar llegada y horarios de proveedores | C41: Planner | D41: 5 días antes | F41: =IF(E41="✓","✅ Completado","⏳ Pendiente") -> ⏳ Pendiente
A42: 34 | B42: Prueba de menú final con catering | C42: Planner + Catering | D42: 5 días antes | F42: =IF(E42="✓","✅ Completado","⏳ Pendiente") -> ⏳ Pendiente
A43: 35 | B43: Preparar kit de emergencia del evento | C43: Planner | D43: 4 días antes | F43: =IF(E43="✓","✅ Completado","⏳ Pendiente") -> ⏳ Pendiente
A44: 36 | B44: Ensayo general de coreografía | C44: Coreógrafo + Novios | D44: 4 días antes | F44: =IF(E44="✓","✅ Completado","⏳ Pendiente") -> ⏳ Pendiente
A45: 37 | B45: Realizar pagos pendientes | C45: Familia/Novios | D45: 3 días antes | F45: =IF(E45="✓","✅ Completado","⏳ Pendiente") -> ⏳ Pendiente
A46: 38 | B46: Confirmar montaje y decoración | C46: Planner + Decorador | D46: 2 días antes | F46: =IF(E46="✓","✅ Completado","⏳ Pendiente") -> ⏳ Pendiente
A47: 39 | B47: Ensayo de ceremonia (si aplica) | C47: Planner + Novios | D47: 2 días antes | F47: =IF(E47="✓","✅ Completado","⏳ Pendiente") -> ⏳ Pendiente
A48: 40 | B48: Supervisar montaje completo | C48: Planner | D48: 1 día antes | F48: =IF(E48="✓","✅ Completado","⏳ Pendiente") -> ⏳ Pendiente
A49: 41 | B49: Confirmar logística de transporte | C49: Planner | D49: 1 día antes | F49: =IF(E49="✓","✅ Completado","⏳ Pendiente") -> ⏳ Pendiente
A50: 42 | B50: Revisar lista final de verificación | C50: Planner | D50: Día del evento | F50: =IF(E50="✓","✅ Completado","⏳ Pendiente") -> ⏳ Pendiente
A51: 43 | B51: Coordinar llegada y bienvenida | C51: Planner + Hostess | D51: Día del evento | F51: =IF(E51="✓","✅ Completado","⏳ Pendiente") -> ⏳ Pendiente
A52: 44 | B52: Supervisión total del evento | C52: Planner + Coordinador | D52: Día del evento | F52: =IF(E52="✓","✅ Completado","⏳ Pendiente") -> ⏳ Pendiente

Sheet 🎨 Diseño
A1: 🎨 DISEÑO & CONCEPTO DEL EVENTO
A2: Define la identidad visual y estética de tu evento
A3: 🎭 TIPO DE EVENTO | F3: 🏛️ MONTAJE & EXPERIENCIA
A4: Tipo de evento | B4: Boda | F4: Tipo de montaje | G4: Banquete con mesas redondas
A5: Estilo principal | B5: Elegante / Romántico | F5: Capacidad por mesa | G5: 10 personas
A6: Paleta de colores | B6: Dorado, Blanco y Verde Salvia | F6: Número de mesas | G6: 15
A7: Número de invitados | B7: 150 | F7: Tipo de sillas | G7: Tiffany en blanco
A8: Presupuesto aprox. | B8: $180,000 MXN | F8: Estilo de mantelería | G8: Lino blanco con caminos dorados
A9: Locación | B9: Hacienda | F9: Iluminación | G9: Cálida + acentos dorados
A10: Temporada | B10: Otoño | F10: Tipo de pista | G10: Pista de madera 6x6m
A11: Hora del día | B11: Tarde-Noche | F11: Escenario / Tarima | G11: Tarima 4x3m para entretenimiento
F12: Área lounge | G12: Sí — zona de descanso VIP
A13: 🎨 PALETA DE COLORES | F13: Área kids | G13: No aplica
A14: Color | B14: Nombre | C14: HEX | D14: Uso en el evento
A15: ████ | B15: Dorado Principal | C15: #C9A84C | D15: Lazos, centros de mesa, detalles
A16: ████ | B16: Blanco Marfil | C16: #FAF7F2 | D16: Mantelería, vestido, altar
A17: ████ | B17: Verde Salvia | C17: #7A9E7E | D17: Flores, hojas decorativas
A18: ████ | B18: Negro Carbón | C18: #1A1A1A | D18: Tipografía, marcos, detalles
A19: ████ | B19: Champagne | C19: #F5E6C0 | D19: Ribbon, fondos, iluminación
A21: 🔗 REFERENCIAS & INSPIRACIÓN
A22: Tipo | B22: Link / Usuario | C22: Notas
A23: Tablero Pinterest | B23: https://pinterest.com/mi-evento | C23: Link al tablero de inspiración
A24: Instagram referencia | B24: @primaveraeventsgroup | C24: Cuenta de referencia visual
A25: Locación referencia | B25: https://primaveraeventsgroup.com | C25: Sitio web del salón
A26: Proveedor flores | B26: https://www.instagram.com/floralstudio | C26: Florería de referencia
A27: Fotógrafo | B27: https://www.luismendozaphoto.com | C27: Portfolio fotógrafo

Sheet 💡 Cotizador
A1: 💡 COTIZADOR AUTOMÁTICO
A2: Resumen de servicios seleccionados — genera tu cotización profesional
A3: ⚡ Este cotizador toma automáticamente los servicios marcados como "✓" en el Catálogo
A4: Categoría | B4: Servicio | C4: Costo Estimado | D4: IVA (16%) | E4: Total c/IVA | F4: Notas
A5: Los servicios seleccionados en el Catálogo aparecerán aquí. Usa la hoja 📦 Catálogo y marca ✓ en columna G.
A7: RESUMEN FINANCIERO
A8: Total servicios seleccionados | C8: =IFERROR('📦 Catálogo'!E115,0) -> 0
A9: IVA (16%) | C9: =C8*0.16 -> 0
A10: TOTAL CON IVA | C10: =C8+C9 -> 0
A11: Presupuesto disponible | C11: ='📊 Dashboard'!B10 -> 180000
A12: Diferencia (Disponible - Total) | C12: =C11-C10 -> 180000
A14: 📞 ¿Listo para hacer realidad tu evento? Contáctanos: 📱 WhatsApp: +52 777-123-4567 | 🌐 primaveraeventsgroup.com | 📧 hola@primaveraeventsgroup.com
